libb/__init__.py
libb/_docs.py
libb/_libb.cpython-310-aarch64-linux-gnu.so
libb/_rust.py
libb/attrdict.py
libb/chart.py
libb/classes.py
libb/config.py
libb/crypto.py
libb/dicts.py
libb/dir.py
libb/exception.py
libb/format.py
libb/func.py
libb/future.py
libb/geo.py
libb/heap.py
libb/iolib.py
libb/iter.py
libb/mime.py
libb/mime.types
libb/module.py
libb/orderedset.py
libb/pandasutils.py
libb/path.py
libb/proc.py
libb/rand.py
libb/signals.py
libb/stats.py
libb/stream.py
libb/sync.py
libb/text.py
libb/thread.py
libb/typedefs.py
libb/util.py
libb/webapp.py
libb/win.py
libb.libs/libgcc_s-9d28dc04.so.1
libb_util-0.0.31.dist-info/METADATA
libb_util-0.0.31.dist-info/WHEEL
libb_util-0.0.31.dist-info/licenses/LICENSE
libb_util-0.0.31.dist-info/licenses/rust/LICENSE
libb_util-0.0.31.dist-info/RECORD
