Metadata-Version: 2.4
Name: libb-util
Version: 0.0.31
Classifier: Programming Language :: Python :: 3
Classifier: Programming Language :: Python :: 3.9
Classifier: Programming Language :: Python :: 3.10
Classifier: Programming Language :: Python :: 3.11
Classifier: Programming Language :: Python :: 3.12
Classifier: Programming Language :: Python :: 3.13
Requires-Dist: numpy
Requires-Dist: backoff
Requires-Dist: regex
Requires-Dist: titlecase>=2.4.1
Requires-Dist: more-itertools
Requires-Dist: wrapt
Requires-Dist: psutil
Requires-Dist: requests
Requires-Dist: tqdm
Requires-Dist: trace-dkey==0.0.6
Requires-Dist: platformdirs
Requires-Dist: typing-extensions
Requires-Dist: bump2version ; extra == 'deploy'
Requires-Dist: sphinx ; extra == 'docs'
Requires-Dist: sphinx-rtd-theme ; extra == 'docs'
Requires-Dist: sphinx-autodoc-typehints ; extra == 'docs'
Requires-Dist: myst-parser ; extra == 'docs'
Requires-Dist: sphinx-copybutton ; extra == 'docs'
Requires-Dist: matplotlib ; extra == 'math'
Requires-Dist: pyarrow ; extra == 'pandas'
Requires-Dist: pandas ; extra == 'pandas'
Requires-Dist: pandas-downcast==1.2.4 ; extra == 'pandas'
Requires-Dist: numexpr ; extra == 'pandas'
Requires-Dist: asserts ; extra == 'test'
Requires-Dist: pytest ; extra == 'test'
Requires-Dist: pytest-mock ; extra == 'test'
Requires-Dist: pytest-runner ; extra == 'test'
Requires-Dist: pytest-benchmark ; extra == 'test'
Requires-Dist: unittest2 ; extra == 'test'
Requires-Dist: webtest ; extra == 'test'
Requires-Dist: maturin>=1.0,<2.0 ; extra == 'test'
Requires-Dist: exceptiongroup ; extra == 'test'
Requires-Dist: jinja2 ; extra == 'test'
Requires-Dist: ftfy ; extra == 'text'
Requires-Dist: rapidfuzz ; extra == 'text'
Requires-Dist: chardet ; extra == 'text'
Requires-Dist: twisted ; extra == 'twd'
Requires-Dist: service-identity ; extra == 'twd'
Requires-Dist: twisted ; extra == 'web'
Requires-Dist: service-identity ; extra == 'web'
Requires-Dist: flask ; extra == 'web'
Provides-Extra: deploy
Provides-Extra: docs
Provides-Extra: math
Provides-Extra: pandas
Provides-Extra: test
Provides-Extra: text
Provides-Extra: twd
Provides-Extra: web
License-File: rust/LICENSE
License-File: LICENSE
Summary: libb utility modules for python
Author-email: bissli <bissli@xyz.org>
License: 0BSD
Requires-Python: >=3.9
